cloudpickle/__init__.py
cloudpickle/cloudpickle.py
cloudpickle/cloudpickle_fast.py
cloudpickle-1.4.1.dist-info/LICENSE
cloudpickle-1.4.1.dist-info/METADATA
cloudpickle-1.4.1.dist-info/WHEEL
cloudpickle-1.4.1.dist-info/top_level.txt
cloudpickle-1.4.1.dist-info/RECORD
